abava/__init__.py
abava/_version.py
abava/abava_data.py
abava/api.py
abava/const.py
abava/exception.py
abava/check/__init__.py
abava/check/check.py
abava/check/statistics.py
abava/export_format/__init__.py
abava/export_format/export.py
abava/export_format/coco/__init__.py
abava/export_format/coco/coco.py
abava/export_format/coco/export_coco.py
abava/export_format/kitti/__init__.py
abava/export_format/kitti/export_kitti.py
abava/export_format/kitti/kitti.py
abava/export_format/labelme/__init__.py
abava/export_format/labelme/export_labelme.py
abava/export_format/labelme/labelme.py
abava/export_format/mask/__init__.py
abava/export_format/mask/generate_mask.py
abava/export_format/voc/__init__.py
abava/export_format/voc/export_voc.py
abava/export_format/voc/voc.py
abava/export_format/yolo/__init__.py
abava/export_format/yolo/export_yolo.py
abava/export_format/yolo/yolo.py
abava/factory/__init__.py
abava/factory/data_factory.py
abava/post_process/__init__.py
abava/post_process/process.py
abava/post_process/coco/__init__.py
abava/post_process/coco/coco_postprocess.py
abava/post_process/coco/test.py
abava/utils/__init__.py
abava/utils/cv_tools.py
abava/utils/general.py
abava/utils/pc_tools.py
abava/visualize/__init__.py
abava/visualize/visual.py
abava/visualize/coco/__init__.py
abava/visualize/coco/visual_coco.py
abava/visualize/labelme/__init__.py
abava/visualize/labelme/visual_labelme.py
abava/visualize/source/__init__.py
abava/visualize/source/visual_source.py
abava/visualize/voc/__init__.py
abava/visualize/voc/visual_voc.py
abava/visualize/yolo/__init__.py
abava/visualize/yolo/visual_yolo.py
Abava_SDK-1.0.9.dist-info/LICENSE
Abava_SDK-1.0.9.dist-info/METADATA
Abava_SDK-1.0.9.dist-info/WHEEL
Abava_SDK-1.0.9.dist-info/top_level.txt
Abava_SDK-1.0.9.dist-info/RECORD
