Metadata-Version: 2.1
Name: Abava-SDK
Version: 1.0.9
Summary: abavaSDK
Author: Xinjun Wu
Author-email: wxj@molardata.com
License-File: LICENSE
Requires-Dist: lxml (>=4.9)
Requires-Dist: numpy (>=1.25)
Requires-Dist: opencv-python (>=4.8)
Requires-Dist: Pillow (>=10.0)
Requires-Dist: Requests (>=2.31)
Requires-Dist: tqdm (>=4.66)
Requires-Dist: dynaconf (>=3.2)
Requires-Dist: scipy
Requires-Dist: dask
Requires-Dist: dask-expr
Requires-Dist: python-lzf (>=0.2.4)
